termcolor_enum/__init__.py
termcolor_enum/enums.py
termcolor_enum/termcolor.py
termcolor_enum-1.2.0.dist-info/LICENSE.txt
termcolor_enum-1.2.0.dist-info/WHEEL
termcolor_enum-1.2.0.dist-info/METADATA
termcolor_enum-1.2.0.dist-info/RECORD
