Metadata-Version: 2.1
Name: termcolor-enum
Version: 1.2.0
Summary: Drop-in [termcolor](https://pypi.org/project/termcolor/) replacement with enums and type hinting
Home-page: https://gitlab.com/TheBicameralMind/termcolor-enum
License: MIT
Author: aidan
Author-email: achaplin3@gatech.edu
Requires-Python: >=3.5,<4.0
Classifier: License :: OSI Approved :: MIT License
Classifier: Programming Language :: Python :: 3
Classifier: Programming Language :: Python :: 3.10
Classifier: Programming Language :: Python :: 3.5
Classifier: Programming Language :: Python :: 3.6
Classifier: Programming Language :: Python :: 3.7
Classifier: Programming Language :: Python :: 3.8
Classifier: Programming Language :: Python :: 3.9
